odoo/addons/stock_warehouse_orderpoint_stock_info_unreserved/README.rst
odoo/addons/stock_warehouse_orderpoint_stock_info_unreserved/__init__.py
odoo/addons/stock_warehouse_orderpoint_stock_info_unreserved/__manifest__.py
odoo/addons/stock_warehouse_orderpoint_stock_info_unreserved/i18n/de.po
odoo/addons/stock_warehouse_orderpoint_stock_info_unreserved/i18n/es.po
odoo/addons/stock_warehouse_orderpoint_stock_info_unreserved/i18n/es_ES.po
odoo/addons/stock_warehouse_orderpoint_stock_info_unreserved/i18n/pt_BR.po
odoo/addons/stock_warehouse_orderpoint_stock_info_unreserved/i18n/sl.po
odoo/addons/stock_warehouse_orderpoint_stock_info_unreserved/models/__init__.py
odoo/addons/stock_warehouse_orderpoint_stock_info_unreserved/models/stock_warehouse_orderpoint.py
odoo/addons/stock_warehouse_orderpoint_stock_info_unreserved/static/description/icon.png
odoo/addons/stock_warehouse_orderpoint_stock_info_unreserved/tests/__init__.py
odoo/addons/stock_warehouse_orderpoint_stock_info_unreserved/tests/test_stock_warehouse_orderpoint.py
odoo/addons/stock_warehouse_orderpoint_stock_info_unreserved/views/stock_warehouse_orderpoint_view.xml
odoo11_addon_stock_warehouse_orderpoint_stock_info_unreserved-11.0.1.0.0.dist-info/DESCRIPTION.rst
odoo11_addon_stock_warehouse_orderpoint_stock_info_unreserved-11.0.1.0.0.dist-info/METADATA
odoo11_addon_stock_warehouse_orderpoint_stock_info_unreserved-11.0.1.0.0.dist-info/RECORD
odoo11_addon_stock_warehouse_orderpoint_stock_info_unreserved-11.0.1.0.0.dist-info/WHEEL
odoo11_addon_stock_warehouse_orderpoint_stock_info_unreserved-11.0.1.0.0.dist-info/metadata.json
odoo11_addon_stock_warehouse_orderpoint_stock_info_unreserved-11.0.1.0.0.dist-info/top_level.txt
